xtg/__init__.py
xtg/calculater.py
xtg/diagnostics.py
xtg/metrics.py
xtg/select.py
xtg/core/__init__.py
xtg/core/kernels.py
xtg/core/weights.py
xtg/models/__init__.py
xtg/models/agwr.py
xtg/models/agwr_pc.py
xtg/models/gwr.py
xtg/models/gwr_knn.py
xtg/models/mgwr.py
xtg/models/ols.py
xtg/models/sgwr.py
xtg-0.0.7.dist-info/METADATA
xtg-0.0.7.dist-info/WHEEL
xtg-0.0.7.dist-info/top_level.txt
xtg-0.0.7.dist-info/RECORD
