Metadata-Version: 2.4
Name: xtg
Version: 0.0.7
Summary: a map tool
Author: mjs
Author-email: mengjinsui@buaa.edu.cn
Requires-Python: >=3.9
Requires-Dist: numpy
Requires-Dist: scipy
Requires-Dist: pysal
Requires-Dist: scikit-learn
Requires-Dist: pandas
Dynamic: author
Dynamic: author-email
Dynamic: description
Dynamic: description-content-type
Dynamic: requires-dist
Dynamic: requires-python
Dynamic: summary
